yhttp/ext/pony/__init__.py
yhttp/ext/pony/cli.py
yhttp/ext/pony/install.py
yhttp/ext/pony/orm.py
yhttp_pony-5.0.1.dist-info/LICENSE
yhttp_pony-5.0.1.dist-info/METADATA
yhttp_pony-5.0.1.dist-info/WHEEL
yhttp_pony-5.0.1.dist-info/top_level.txt
yhttp_pony-5.0.1.dist-info/RECORD
