Metadata-Version: 2.1
Name: yhttp-pony
Version: 5.0.1
Summary: A very micro http framework.
Home-page: http://github.com/yhttp/yhttp-pony
Author: Vahid Mardani
Author-email: vahid.mardani@gmail.com
License: MIT
Classifier: Environment :: Console
Classifier: Environment :: Web Environment
Classifier: Intended Audience :: Developers
Classifier: Natural Language :: English
Classifier: Development Status :: 5 - Production/Stable
Classifier: License :: Other/Proprietary License
Classifier: Operating System :: OS Independent
Classifier: Programming Language :: Python :: 3.6
Classifier: Topic :: Software Development
Classifier: Topic :: Internet :: WWW/HTTP
Classifier: Topic :: Internet :: WWW/HTTP :: Dynamic Content
Classifier: Topic :: Internet :: WWW/HTTP :: WSGI :: Application
Classifier: Topic :: Software Development :: Libraries
Classifier: Topic :: Software Development :: Libraries :: Python Modules
License-File: LICENSE
Requires-Dist: yhttp <7,>=6.2
Requires-Dist: yhttp-dbmanager <6,>=5.0.1
Requires-Dist: pony
